loops_unofficial/__init__.py
loops_unofficial/async_client.py
loops_unofficial/client.py
loops_unofficial/types.py
loops_python_unofficial-0.1.0.dist-info/METADATA
loops_python_unofficial-0.1.0.dist-info/WHEEL
loops_python_unofficial-0.1.0.dist-info/licenses/LICENSE
loops_python_unofficial-0.1.0.dist-info/RECORD
