Metadata-Version: 2.4
Name: loops-python-unofficial
Version: 0.1.0
Summary: Unofficial Python SDK for Loops (loops.so) with sync and async clients
Project-URL: Homepage, https://loops.so
Project-URL: Repository, https://github.com/VersionLens/loops-python-unofficial
Project-URL: Documentation, https://loops.so/docs
Author-email: VersionLens <support@versionlens.com>
License: MIT
License-File: LICENSE
Keywords: email,loops,marketing,sdk,transactional
Classifier: Development Status :: 3 - Alpha
Classifier: Intended Audience :: Developers
Classifier: License :: OSI Approved :: MIT License
Classifier: Programming Language :: Python
Classifier: Programming Language :: Python :: 3
Classifier: Programming Language :: Python :: 3 :: Only
Classifier: Programming Language :: Python :: 3.9
Classifier: Programming Language :: Python :: 3.10
Classifier: Programming Language :: Python :: 3.11
Classifier: Programming Language :: Python :: 3.12
Classifier: Programming Language :: Python :: 3.13
Classifier: Topic :: Software Development :: Libraries
Classifier: Typing :: Typed
Requires-Python: >=3.9
Requires-Dist: httpx>=0.27.0
